{
  "$schema": "../../assetlist.schema.json",
  "chain_name": "altheatestnet",
  "assets": [
    {
      "description": "The native staking token of the Althea Blockchain",
      "denom_units": [
        {
          "denom": "ualthea",
          "exponent": 0
        },
        {
          "denom": "althea",
          "exponent": 18
        }
      ],
      "base": "ualthea",
      "name": "Althea",
      "display": "althea",
      "symbol": "ALTHEA",
      "logo_URIs": {
        "png": "https://raw.githubusercontent.com/cosmos/chain-registry/master/testnets/altheatestnet/images/althea.png"
      },
      "images": [
        {
          "png": "https://raw.githubusercontent.com/cosmos/chain-registry/master/testnets/altheatestnet/images/althea.png"
        }
      ]
    }
  ]
}
